project/src/fsm_controller.v
module fsm_controller (
    input clk,
    input reset,
    input [31:0] address,
    input rw,
    input [1:0] privilege,
    input intrusion_detected,
    output reg log_en,
    output reg access_granted,
    output reg access_denied,
    output reg alert
);
    localparam IDLE = 2'b00, EVAL = 2'b01, RESOLVE = 2'b10;
    reg [1:0] state;

    reg [31:0] last_addr;
    reg last_rw;
    reg [1:0] last_priv;
    
    // Detect new access request
    wire new_request = (address != last_addr) || (rw != last_rw) || (privilege != last_priv);

    always @(posedge clk or posedge reset) begin
        if (reset) begin
            state <= IDLE;
            log_en <= 1'b0;
            access_granted <= 1'b0;
            access_denied <= 1'b0;
            alert <= 1'b0;
            last_addr <= 32'hFFFF_FFFF; // Initialization to unusual state
            last_rw <= 1'b0;
            last_priv <= 2'b0;
        end else begin
            case (state)
                IDLE: begin
                    log_en <= 1'b0;
                    if (new_request) begin
                        last_addr <= address;
                        last_rw <= rw;
                        last_priv <= privilege;
                        state <= EVAL;
                        
                        // Clear flags on new request
                        access_granted <= 1'b0;
                        access_denied <= 1'b0;
                        alert <= 1'b0;
                    end
                end
                EVAL: begin
                    if (intrusion_detected) begin
                        access_denied <= 1'b1;
                        alert <= 1'b1;
                        log_en <= 1'b1; // Trigger logging mechanisms
                    end else begin
                        access_granted <= 1'b1;
                    end
                    state <= RESOLVE;
                end
                RESOLVE: begin
                    log_en <= 1'b0; // Log is a one-clock pulse
                    if (new_request) begin
                        last_addr <= address;
                        last_rw <= rw;
                        last_priv <= privilege;
                        state <= EVAL;
                        
                        // Clear flags
                        access_granted <= 1'b0;
                        access_denied <= 1'b0;
                        alert <= 1'b0;
                    end
                end
            endcase
        end
    end
endmodule

project/src/region_lock.v
module region_lock (
    input clk,
    input reset,
    input [3:0] region,
    input log_en,
    input [1:0] threat_level,
    output reg [15:0] locked_regions
);
    // Track violations per region
    reg [7:0] region_violations [0:15];
    integer i;

    always @(posedge clk or posedge reset) begin
        if (reset) begin
            locked_regions <= 16'b0;
            for (i=0; i<16; i=i+1) begin
                region_violations[i] <= 8'd0;
            end
        end else if (log_en) begin
            if (region_violations[region] < 8'hFF)
                region_violations[region] <= region_violations[region] + 1'b1;
            
            // Region lock trigger: ONLY if threat level is CRITICAL
            // and threshold (4 violations in region) is met.
            if (threat_level == 2'b11 && region_violations[region] >= 8'd4) 
                locked_regions[region] <= 1'b1;
        end
    end
endmodule

project/src/threat_analysis.v
module threat_analysis (
    input clk,
    input reset,
    input log_en,
    input [31:0] address,
    input [7:0] total_violations,
    output reg [1:0] threat_level
);
    reg [31:0] last_attack_addr;
    reg [3:0] repeated_attack_cnt;
    reg [3:0] scan_cnt;

    // Threat Levels: 00=NORMAL, 01=SUSPICIOUS, 10=ATTACK, 11=CRITICAL
    always @(posedge clk or posedge reset) begin
        if (reset) begin
            threat_level <= 2'b00;
            last_attack_addr <= 32'h0;
            repeated_attack_cnt <= 4'd0;
            scan_cnt <= 4'd0;
        end else if (log_en) begin
            // 1. Pattern Detection Logic
            if (address == last_attack_addr) begin
                if (repeated_attack_cnt < 4'hF)
                    repeated_attack_cnt <= repeated_attack_cnt + 1'b1;
                scan_cnt <= 4'd0; 
            end else if (address == last_attack_addr + 32'd4) begin
                if (scan_cnt < 4'hF)
                    scan_cnt <= scan_cnt + 1'b1;
                repeated_attack_cnt <= 4'd0;
            end else begin
                repeated_attack_cnt <= 4'd0;
                scan_cnt <= 4'd0;
            end
            
            last_attack_addr <= address;

            // 2. Threshold-based Evaluation
            // Base evaluation on total violations
            if (total_violations >= 8'd7)
                threat_level <= 2'b11; // CRITICAL
            else if (total_violations >= 8'd5)
                threat_level <= 2'b10; // ATTACK
            else if (total_violations >= 8'd3)
                threat_level <= 2'b01; // SUSPICIOUS
            else
                threat_level <= 2'b00; // NORMAL

            // 3. Pattern Override (Accelerate escalation)
            if (repeated_attack_cnt >= 4'd3 || scan_cnt >= 4'd3) begin
                if (threat_level < 2'b10) threat_level <= 2'b10; // Jump to ATTACK
            end
            if (repeated_attack_cnt >= 4'd5 || scan_cnt >= 4'd5) begin
                threat_level <= 2'b11; // Jump to CRITICAL
            end
        end
    end
endmodule

project/src/logger.v
module logger (
    input clk,
    input reset,
    input log_en,
    input [31:0] address,
    input [3:0] region,
    input rw,
    input [1:0] privilege
);
    // Circular buffer to store the last 4 violations
    reg [40:0] log_buffer [0:3];
    reg [1:0] ptr;

    always @(posedge clk or posedge reset) begin
        if (reset) begin
            ptr <= 2'b0;
            log_buffer[0] <= 41'b0;
            log_buffer[1] <= 41'b0;
            log_buffer[2] <= 41'b0;
            log_buffer[3] <= 41'b0;
        end else if (log_en) begin
            log_buffer[ptr] <= {address, region, rw, privilege};
            ptr <= ptr + 1'b1;
        end
    end
endmodule

project/src/violation_counter.v
module violation_counter (
    input clk,
    input reset,
    input log_en,
    output reg [7:0] total_violations
);
    // Tracks total violations in the system
    always @(posedge clk or posedge reset) begin
        if (reset)
            total_violations <= 8'd0;
        else if (log_en) begin
            // Saturating counter
            if (total_violations < 8'hFF)
                total_violations <= total_violations + 1'b1;
        end
    end
endmodule

project/src/intrusion_detection.v
module intrusion_detection (
    input is_valid,
    input is_locked,
    input [1:0] privilege,
    output intrusion_detected
);
    // An intrusion is either an invalid access attempt 
    // OR accessing a locked region while having LOW privilege (USER or SYSTEM).
    // KERNEL (2'b10) and SECURE (2'b11) are allowed to bypass region locks.
    assign intrusion_detected = (~is_valid) | (is_locked && (privilege < 2'b10));
endmodule

project/src/access_control.v
module access_control (
    input [1:0] privilege,
    input rw, // 0 = read, 1 = write
    input [1:0] req_privilege,
    input readonly,
    output is_valid
);
    // Check if input privilege is greater or equal to required
    wire priv_ok = (privilege >= req_privilege);
    
    // Check if write is attempted on read-only region
    wire rw_ok = ~(rw & readonly);
    
    // Valid access requires both privilege clearance and correct R/W operation
    assign is_valid = priv_ok & rw_ok;
endmodule

project/src/policy_engine.v
module policy_engine (
    input [3:0] region,
    output reg [1:0] req_privilege,
    output reg readonly
);
    // Privilege levels: 00=user, 01=system, 10=kernel, 11=secure
    always @(*) begin
        case (region)
            4'd0: begin req_privilege = 2'b00; readonly = 1'b0; end // User: RW
            4'd1: begin req_privilege = 2'b01; readonly = 1'b0; end // System: RW
            4'd2: begin req_privilege = 2'b10; readonly = 1'b1; end // Kernel: RO
            4'd3: begin req_privilege = 2'b11; readonly = 1'b0; end // Secure: RW
            4'd4: begin req_privilege = 2'b10; readonly = 1'b0; end // Ext Kernel: RW
            default: begin req_privilege = 2'b11; readonly = 1'b1; end // Default: Secure RO
        endcase
    end
endmodule

project/src/region_decoder.v
module region_decoder (
    input [31:0] address,
    output reg [3:0] region
);
    // MSB-based region decoding
    always @(*) begin
        case (address[31:28])
            4'h0: region = 4'd0;  // User Region
            4'h1: region = 4'd1;  // System Region
            4'h2: region = 4'd2;  // Kernel Region
            4'h3: region = 4'd3;  // Secure Region
            4'h4: region = 4'd4;
            4'h5: region = 4'd5;
            default: region = 4'd15; // Unmapped / Default Secure
        endcase
    end
endmodule

project/src/memory_firewall_top.v
module memory_firewall_top (
    input clk,
    input reset,
    input [31:0] address,
    input rw,
    input [1:0] privilege,
    output access_granted,
    output access_denied,
    output alert,
    output [1:0] threat_level,
    output [7:0] total_violations // Exposed for TB viewing convenience
);

    wire [3:0] region;
    wire [1:0] req_privilege;
    wire readonly;
    wire is_valid;
    wire intrusion_detected;
    wire log_en;
    wire [15:0] locked_regions;
    wire is_locked;

    // Structural Instantiations
    region_decoder u_region_decoder (
        .address(address),
        .region(region)
    );

    policy_engine u_policy_engine (
        .region(region),
        .req_privilege(req_privilege),
        .readonly(readonly)
    );

    access_control u_access_control (
        .privilege(privilege),
        .rw(rw),
        .req_privilege(req_privilege),
        .readonly(readonly),
        .is_valid(is_valid)
    );

    assign is_locked = locked_regions[region];

    intrusion_detection u_intrusion_detection (
        .is_valid(is_valid),
        .is_locked(is_locked),
        .privilege(privilege),
        .intrusion_detected(intrusion_detected)
    );

    violation_counter u_violation_counter (
        .clk(clk),
        .reset(reset),
        .log_en(log_en),
        .total_violations(total_violations)
    );

    logger u_logger (
        .clk(clk),
        .reset(reset),
        .log_en(log_en),
        .address(address),
        .region(region),
        .rw(rw),
        .privilege(privilege)
    );

    threat_analysis u_threat_analysis (
        .clk(clk),
        .reset(reset),
        .log_en(log_en),
        .address(address),
        .total_violations(total_violations),
        .threat_level(threat_level)
    );

    region_lock u_region_lock (
        .clk(clk),
        .reset(reset),
        .region(region),
        .log_en(log_en),
        .threat_level(threat_level),
        .locked_regions(locked_regions)
    );

    fsm_controller u_fsm_controller (
        .clk(clk),
        .reset(reset),
        .address(address),
        .rw(rw),
        .privilege(privilege),
        .intrusion_detected(intrusion_detected),
        .log_en(log_en),
        .access_granted(access_granted),
        .access_denied(access_denied),
        .alert(alert)
    );

endmodule

project/tb/memory_firewall_tb.v
`timescale 1ns/1ps

module memory_firewall_tb;

    // Inputs
    reg clk;
    reg reset;
    reg [31:0] address;
    reg rw;
    reg [1:0] privilege;

    // Outputs
    wire access_granted;
    wire access_denied;
    wire alert;
    wire [1:0] threat_level;
    wire [7:0] total_violations;

    // Instantiate Top Module
    memory_firewall_top uut (
        .clk(clk),
        .reset(reset),
        .address(address),
        .rw(rw),
        .privilege(privilege),
        .access_granted(access_granted),
        .access_denied(access_denied),
        .alert(alert),
        .threat_level(threat_level),
        .total_violations(total_violations)
    );

    // Clock Generation
    always #5 clk = ~clk;

    // Helper Task for submitting requests
    task make_request(input [31:0] addr, input write_en, input [1:0] priv, input [8*20:1] desc);
        begin
            $display("--- %s ---", desc);
            // Drive inputs
            address = addr;
            rw = write_en;
            privilege = priv;
            
            // Wait for FSM to Evaluate and Resolve
            @(posedge access_granted or posedge access_denied);
            #1; // Output stability margin
            
            // Log status
            $display("Addr:%h RW:%b Priv:%b | Gran:%b Den:%b Alrt:%b ThrLv:%b V_Cnt:%d\n",
                address, rw, privilege, access_granted, access_denied, alert, threat_level, total_violations);
            
            // Wait a few cycles before next transaction
            #20; 
        end
    endtask

    initial begin
        // Initialize Inputs
        clk = 0;
        reset = 1;
        address = 32'b0;
        rw = 0;
        privilege = 2'b00;

        // VCD Dump
        $dumpfile("memory_firewall.vcd");
        $dumpvars(0, memory_firewall_tb);

        // De-assert reset
        #20;
        reset = 0;
        #20;

        $display("======= STARTING MEMORY FIREWALL TESTBENCH =======");

        // 1. Normal Access: User Privilege reading User Region
        make_request(32'h0000_1000, 0, 2'b00, "Normal Read User Region");
        
        // 2. Illegal Kernel Write
        make_request(32'h2000_1000, 1, 2'b10, "Illegal Kernel Write");

        // 3. User Writing System (Escalation to SUSPICIOUS at V=3)
        make_request(32'h1000_1000, 1, 2'b00, "Violation 1");
        make_request(32'h1000_1004, 1, 2'b00, "Violation 2");
        make_request(32'h1000_1008, 1, 2'b00, "Violation 3 (SUSPICION)");

        // 4. Sequential Scan Detector Test (Should jump to ATTACK)
        make_request(32'h4000_0000, 0, 2'b00, "Scan 1");
        make_request(32'h4000_0004, 0, 2'b00, "Scan 2");
        make_request(32'h4000_0008, 0, 2'b00, "Scan 3 (ATTACK JUMP)");

        // 5. Reaching CRITICAL (V >= 7) and Locking Region 4 (Ext Kernel)
        // Region 4 is 0x4...
        make_request(32'h4000_1000, 1, 2'b00, "Viol 4 (on Reg 4)");
        make_request(32'h4000_1004, 1, 2'b00, "Viol 5 (on Reg 4)");
        make_request(32'h4000_1008, 1, 2'b00, "Viol 6 (on Reg 4)");
        make_request(32'h4000_100C, 1, 2'b00, "Viol 7 (CRITICAL & LOCK)");

        // 6. Privilege Bypass Test
        // Region 4 is locked. USER (2'b00) should be denied, 
        // but KERNEL (2'b10) should be granted (Region 4 normally allows KERNEL).
        make_request(32'h4000_2000, 0, 2'b00, "USER on Locked (Deny)");
        make_request(32'h4000_2004, 0, 2'b10, "KERNEL on Locked (Grant)");

        $display("======= SIMULATION COMPLETE =======");
        $finish;
    end

endmodule

project/memory_firewall.vcd
$date
	Mon Apr 20 00:04:04 2026
$end
$version
	Icarus Verilog
$end
$timescale
	1ps
$end
$scope module memory_firewall_tb $end
$var wire 8 ! total_violations [7:0] $end
$var wire 2 " threat_level [1:0] $end
$var wire 1 # alert $end
$var wire 1 $ access_granted $end
$var wire 1 % access_denied $end
$var reg 32 & address [31:0] $end
$var reg 1 ' clk $end
$var reg 2 ( privilege [1:0] $end
$var reg 1 ) reset $end
$var reg 1 * rw $end
$scope module uut $end
$var wire 32 + address [31:0] $end
$var wire 1 ' clk $end
$var wire 2 , privilege [1:0] $end
$var wire 1 ) reset $end
$var wire 1 * rw $end
$var wire 8 - total_violations [7:0] $end
$var wire 2 . threat_level [1:0] $end
$var wire 2 / req_privilege [1:0] $end
$var wire 4 0 region [3:0] $end
$var wire 1 1 readonly $end
$var wire 1 2 log_en $end
$var wire 16 3 locked_regions [15:0] $end
$var wire 1 4 is_valid $end
$var wire 1 5 is_locked $end
$var wire 1 6 intrusion_detected $end
$var wire 1 # alert $end
$var wire 1 $ access_granted $end
$var wire 1 % access_denied $end
$scope module u_access_control $end
$var wire 1 4 is_valid $end
$var wire 2 7 privilege [1:0] $end
$var wire 1 * rw $end
$var wire 1 8 rw_ok $end
$var wire 2 9 req_privilege [1:0] $end
$var wire 1 1 readonly $end
$var wire 1 : priv_ok $end
$upscope $end
$scope module u_fsm_controller $end
$var wire 32 ; address [31:0] $end
$var wire 1 ' clk $end
$var wire 1 < new_request $end
$var wire 2 = privilege [1:0] $end
$var wire 1 ) reset $end
$var wire 1 * rw $end
$var wire 1 6 intrusion_detected $end
$var parameter 2 > EVAL $end
$var parameter 2 ? IDLE $end
$var parameter 2 @ RESOLVE $end
$var reg 1 % access_denied $end
$var reg 1 $ access_granted $end
$var reg 1 # alert $end
$var reg 32 A last_addr [31:0] $end
$var reg 2 B last_priv [1:0] $end
$var reg 1 C last_rw $end
$var reg 1 2 log_en $end
$var reg 2 D state [1:0] $end
$upscope $end
$scope module u_intrusion_detection $end
$var wire 1 6 intrusion_detected $end
$var wire 1 5 is_locked $end
$var wire 1 4 is_valid $end
$var wire 2 E privilege [1:0] $end
$upscope $end
$scope module u_logger $end
$var wire 32 F address [31:0] $end
$var wire 1 ' clk $end
$var wire 1 2 log_en $end
$var wire 2 G privilege [1:0] $end
$var wire 1 ) reset $end
$var wire 1 * rw $end
$var wire 4 H region [3:0] $end
$var reg 2 I ptr [1:0] $end
$upscope $end
$scope module u_policy_engine $end
$var wire 4 J region [3:0] $end
$var reg 1 1 readonly $end
$var reg 2 K req_privilege [1:0] $end
$upscope $end
$scope module u_region_decoder $end
$var wire 32 L address [31:0] $end
$var reg 4 M region [3:0] $end
$upscope $end
$scope module u_region_lock $end
$var wire 1 ' clk $end
$var wire 1 2 log_en $end
$var wire 4 N region [3:0] $end
$var wire 1 ) reset $end
$var wire 2 O threat_level [1:0] $end
$var reg 16 P locked_regions [15:0] $end
$var integer 32 Q i [31:0] $end
$upscope $end
$scope module u_threat_analysis $end
$var wire 32 R address [31:0] $end
$var wire 1 ' clk $end
$var wire 1 2 log_en $end
$var wire 1 ) reset $end
$var wire 8 S total_violations [7:0] $end
$var reg 32 T last_attack_addr [31:0] $end
$var reg 4 U repeated_attack_cnt [3:0] $end
$var reg 4 V scan_cnt [3:0] $end
$var reg 2 W threat_level [1:0] $end
$upscope $end
$scope module u_violation_counter $end
$var wire 1 ' clk $end
$var wire 1 2 log_en $end
$var wire 1 ) reset $end
$var reg 8 X total_violations [7:0] $end
$upscope $end
$upscope $end
$scope task make_request $end
$var reg 32 Y addr [31:0] $end
$var reg 160 Z desc [160:1] $end
$var reg 2 [ priv [1:0] $end
$var reg 1 \ write_en $end
$upscope $end
$upscope $end
$enddefinitions $end
$comment Show the parameter values. $end
$dumpall
b10 @
b0 ?
b1 >
$end
#0
$dumpvars
x\
bx [
bx Z
bx Y
b0 X
b0 W
b0 V
b0 U
b0 T
b0 S
b0 R
b10000 Q
b0 P
b0 O
b0 N
b0 M
b0 L
b0 K
b0 J
b0 I
b0 H
b0 G
b0 F
b0 E
b0 D
0C
b0 B
b11111111111111111111111111111111 A
b0 =
1<
b0 ;
1:
b0 9
18
b0 7
06
05
14
b0 3
02
01
b0 0
b0 /
b0 .
b0 -
b0 ,
b0 +
0*
1)
b0 (
0'
b0 &
0%
0$
0#
b0 "
b0 !
$end
#5000
b10000 Q
1'
#10000
0'
#15000
b10000 Q
1'
#20000
0'
0)
#25000
0<
b1 D
b0 A
1'
#30000
0'
#35000
b10 D
1$
1'
#40000
1<
0'
b1000000000000 &
b1000000000000 +
b1000000000000 ;
b1000000000000 F
b1000000000000 L
b1000000000000 R
b110110101100001011011000010000001010010011001010110000101100100001000000101010101110011011001010111001000100000010100100110010101100111011010010110111101101110 Z
b0 [
0\
b1000000000000 Y
#45000
0<
0$
b1 D
b1000000000000 A
1'
#50000
0'
#55000
b10 D
1$
1'
#60000
0'
#65000
1'
#70000
0'
#75000
1'
#76000
16
04
08
11
b10 /
b10 9
b10 K
1<
b10 0
b10 H
b10 J
b10 M
b10 N
b10 (
b10 ,
b10 7
b10 =
b10 E
b10 G
1*
b100000000000000001000000000000 &
b100000000000000001000000000000 +
b100000000000000001000000000000 ;
b100000000000000001000000000000 F
b100000000000000001000000000000 L
b100000000000000001000000000000 R
b100100101101100011011000110010101100111011000010110110000100000010010110110010101110010011011100110010101101100001000000101011101110010011010010111010001100101 Z
b10 [
1\
b100000000000000001000000000000 Y
#80000
0'
#85000
0<
0$
b1 D
b10 B
1C
b100000000000000001000000000000 A
1'
#90000
0'
#95000
b10 D
12
1#
1%
1'
#100000
0'
#105000
02
b100000000000000001000000000000 T
b1 I
b1 !
b1 -
b1 S
b1 X
1'
#110000
0'
#115000
1'
#116000
18
01
b1 /
b1 9
b1 K
1<
b1 0
b1 H
b1 J
b1 M
b1 N
0:
b0 (
b0 ,
b0 7
b0 =
b0 E
b0 G
b10000000000000001000000000000 &
b10000000000000001000000000000 +
b10000000000000001000000000000 ;
b10000000000000001000000000000 F
b10000000000000001000000000000 L
b10000000000000001000000000000 R
b101011001101001011011110110110001100001011101000110100101101111011011100010000000110001 Z
b0 [
b10000000000000001000000000000 Y
#120000
0'
#125000
0<
0#
0%
b1 D
b0 B
b10000000000000001000000000000 A
1'
#130000
0'
#135000
b10 D
12
1#
1%
1'
#140000
0'
#145000
02
b10000000000000001000000000000 T
b10 I
b10 !
b10 -
b10 S
b10 X
1'
#150000
0'
#155000
1'
#156000
1<
b10000000000000001000000000100 &
b10000000000000001000000000100 +
b10000000000000001000000000100 ;
b10000000000000001000000000100 F
b10000000000000001000000000100 L
b10000000000000001000000000100 R
b101011001101001011011110110110001100001011101000110100101101111011011100010000000110010 Z
b10000000000000001000000000100 Y
#160000
0'
#165000
0<
0#
0%
b1 D
b10000000000000001000000000100 A
1'
#170000
0'
#175000
b10 D
12
1#
1%
1'
#180000
0'
#185000
02
b10000000000000001000000000100 T
b1 V
b11 I
b11 !
b11 -
b11 S
b11 X
1'
#190000
0'
#195000
1'
#196000
1<
b10000000000000001000000001000 &
b10000000000000001000000001000 +
b10000000000000001000000001000 ;
b10000000000000001000000001000 F
b10000000000000001000000001000 L
b10000000000000001000000001000 R
b110110001100001011101000110100101101111011011100010000000110011001000000010100001010011010101010101001101010000010010010100001101001001010011110100111000101001 Z
b10000000000000001000000001000 Y
#200000
0'
#205000
0<
0#
0%
b1 D
b10000000000000001000000001000 A
1'
#210000
0'
#215000
b10 D
12
1#
1%
1'
#220000
0'
#225000
02
b1 "
b1 .
b1 O
b1 W
b10000000000000001000000001000 T
b10 V
b0 I
b100 !
b100 -
b100 S
b100 X
1'
#230000
0'
#235000
1'
#236000
1<
b10 /
b10 9
b10 K
b100 0
b100 H
b100 J
b100 M
b100 N
0*
b1000000000000000000000000000000 &
b1000000000000000000000000000000 +
b1000000000000000000000000000000 ;
b1000000000000000000000000000000 F
b1000000000000000000000000000000 L
b1000000000000000000000000000000 R
b10100110110001101100001011011100010000000110001 Z
0\
b1000000000000000000000000000000 Y
#240000
0'
#245000
0<
0#
0%
b1 D
0C
b1000000000000000000000000000000 A
1'
#250000
0'
#255000
b10 D
12
1#
1%
1'
#260000
0'
#265000
02
b1000000000000000000000000000000 T
b0 V
b1 I
b101 !
b101 -
b101 S
b101 X
1'
#270000
0'
#275000
1'
#276000
1<
b1000000000000000000000000000100 &
b1000000000000000000000000000100 +
b1000000000000000000000000000100 ;
b1000000000000000000000000000100 F
b1000000000000000000000000000100 L
b1000000000000000000000000000100 R
b10100110110001101100001011011100010000000110010 Z
b1000000000000000000000000000100 Y
#280000
0'
#285000
0<
0#
0%
b1 D
b1000000000000000000000000000100 A
1'
#290000
0'
#295000
b10 D
12
1#
1%
1'
#300000
0'
#305000
02
b10 "
b10 .
b10 O
b10 W
b1000000000000000000000000000100 T
b1 V
b10 I
b110 !
b110 -
b110 S
b110 X
1'
#310000
0'
#315000
1'
#316000
1<
b1000000000000000000000000001000 &
b1000000000000000000000000001000 +
b1000000000000000000000000001000 ;
b1000000000000000000000000001000 F
b1000000000000000000000000001000 L
b1000000000000000000000000001000 R
b101001101100011011000010110111000100000001100110010000000101000010000010101010001010100010000010100001101001011001000000100101001010101010011010101000000101001 Z
b1000000000000000000000000001000 Y
#320000
0'
#325000
0<
0#
0%
b1 D
b1000000000000000000000000001000 A
1'
#330000
0'
#335000
b10 D
12
1#
1%
1'
#340000
0'
#345000
02
b1000000000000000000000000001000 T
b10 V
b11 I
b111 !
b111 -
b111 S
b111 X
1'
#350000
0'
#355000
1'
#356000
1<
1*
b1000000000000000001000000000000 &
b1000000000000000001000000000000 +
b1000000000000000001000000000000 ;
b1000000000000000001000000000000 F
b1000000000000000001000000000000 L
b1000000000000000001000000000000 R
b101011001101001011011110110110000100000001101000010000000101000011011110110111000100000010100100110010101100111001000000011010000101001 Z
1\
b1000000000000000001000000000000 Y
#360000
0'
#365000
0<
0#
0%
b1 D
1C
b1000000000000000001000000000000 A
1'
#370000
0'
#375000
b10 D
12
1#
1%
1'
#380000
0'
#385000
02
b11 "
b11 .
b11 O
b11 W
b1000000000000000001000000000000 T
b0 V
b0 I
b1000 !
b1000 -
b1000 S
b1000 X
1'
#390000
0'
#395000
1'
#396000
1<
b1000000000000000001000000000100 &
b1000000000000000001000000000100 +
b1000000000000000001000000000100 ;
b1000000000000000001000000000100 F
b1000000000000000001000000000100 L
b1000000000000000001000000000100 R
b101011001101001011011110110110000100000001101010010000000101000011011110110111000100000010100100110010101100111001000000011010000101001 Z
b1000000000000000001000000000100 Y
#400000
0'
#405000
0<
0#
0%
b1 D
b1000000000000000001000000000100 A
1'
#410000
0'
#415000
b10 D
12
1#
1%
1'
#420000
0'
#425000
02
15
b10000 3
b10000 P
b1000000000000000001000000000100 T
b1 V
b1 I
b1001 !
b1001 -
b1001 S
b1001 X
1'
#430000
0'
#435000
1'
#436000
1<
b1000000000000000001000000001000 &
b1000000000000000001000000001000 +
b1000000000000000001000000001000 ;
b1000000000000000001000000001000 F
b1000000000000000001000000001000 L
b1000000000000000001000000001000 R
b101011001101001011011110110110000100000001101100010000000101000011011110110111000100000010100100110010101100111001000000011010000101001 Z
b1000000000000000001000000001000 Y
#440000
0'
#445000
0<
0#
0%
b1 D
b1000000000000000001000000001000 A
1'
#450000
0'
#455000
b10 D
12
1#
1%
1'
#460000
0'
#465000
02
b1000000000000000001000000001000 T
b10 V
b10 I
b1010 !
b1010 -
b1010 S
b1010 X
1'
#470000
0'
#475000
1'
#476000
1<
b1000000000000000001000000001100 &
b1000000000000000001000000001100 +
b1000000000000000001000000001100 ;
b1000000000000000001000000001100 F
b1000000000000000001000000001100 L
b1000000000000000001000000001100 R
b10000000110111001000000010100001000011010100100100100101010100010010010100001101000001010011000010000000100110001000000100110001001111010000110100101100101001 Z
b1000000000000000001000000001100 Y
#480000
0'
#485000
0<
0#
0%
b1 D
b1000000000000000001000000001100 A
1'
#490000
0'
#495000
b10 D
12
1#
1%
1'
#500000
0'
#505000
02
b1000000000000000001000000001100 T
b11 V
b11 I
b1011 !
b1011 -
b1011 S
b1011 X
1'
#510000
0'
#515000
1'
#516000
1<
0*
b1000000000000000010000000000000 &
b1000000000000000010000000000000 +
b1000000000000000010000000000000 ;
b1000000000000000010000000000000 F
b1000000000000000010000000000000 L
b1000000000000000010000000000000 R
b101001101000101010100100010000001101111011011100010000001001100011011110110001101101011011001010110010000100000001010000100010001100101011011100111100100101001 Z
0\
b1000000000000000010000000000000 Y
#520000
0'
#525000
0<
0#
0%
b1 D
0C
b1000000000000000010000000000000 A
1'
#530000
0'
#535000
b10 D
12
1#
1%
1'
#540000
0'
#545000
02
b1000000000000000010000000000000 T
b0 V
b0 I
b1100 !
b1100 -
b1100 S
b1100 X
1'
#550000
0'
#555000
1'
#556000
06
14
1<
1:
b10 (
b10 ,
b10 7
b10 =
b10 E
b10 G
b1000000000000000010000000000100 &
b1000000000000000010000000000100 +
b1000000000000000010000000000100 ;
b1000000000000000010000000000100 F
b1000000000000000010000000000100 L
b1000000000000000010000000000100 R
b100010101001100001000000110111101101110001000000100110001101111011000110110101101100101011001000010000000101000010001110111001001100001011011100111010000101001 Z
b10 [
b1000000000000000010000000000100 Y
#560000
0'
#565000
0<
0#
0%
b1 D
b10 B
b1000000000000000010000000000100 A
1'
#570000
0'
#575000
b10 D
1$
1'
